nuant/__init__.py
nuant/helpers/__init__.py
nuant/helpers/simulation.py
nuant.helpers-0.0.9.dist-info/METADATA
nuant.helpers-0.0.9.dist-info/WHEEL
nuant.helpers-0.0.9.dist-info/top_level.txt
nuant.helpers-0.0.9.dist-info/RECORD
