Metadata-Version: 2.1
Name: nuant.helpers
Version: 0.0.9
Summary: Nuant helpers
Author-email: Nuant <contact@nuant.com>
Project-URL: Homepage, https://www.nuant.com
Classifier: Programming Language :: Python :: 3
Classifier: License :: OSI Approved :: MIT License
Classifier: Operating System :: OS Independent
Requires-Python: >=3.8
Requires-Dist: requests ==2.32.3
Requires-Dist: toml ==0.10.2
